{"trial_id": "0113", "hyperparameters": {"space": [{"class_name": "Int", "config": {"name": "ltc_units", "default": null, "conditions": [], "min_value": 16, "max_value": 64, "step": 16, "sampling": "linear"}}, {"class_name": "Int", "config": {"name": "dense_units", "default": null, "conditions": [], "min_value": 16, "max_value": 64, "step": 16, "sampling": "linear"}}, {"class_name": "Float", "config": {"name": "learning_rate", "default": 0.0001, "conditions": [], "min_value": 0.0001, "max_value": 0.01, "step": null, "sampling": "log"}}], "values": {"ltc_units": 48, "dense_units": 48, "learning_rate": 0.0007943282347242816}}, "metrics": {"metrics": {"loss": {"direction": "min", "observations": [{"value": [0.01017814315855503], "step": 19}]}, "mae": {"direction": "min", "observations": [{"value": [0.07920239120721817], "step": 19}]}, "val_loss": {"direction": "min", "observations": [{"value": [0.00799071416258812], "step": 19}]}, "val_mae": {"direction": "min", "observations": [{"value": [0.06958795338869095], "step": 19}]}}}, "score": 0.00799071416258812, "best_step": 19, "status": "COMPLETED", "message": null}